reactpy_flake8/__init__.py
reactpy_flake8/common.py
reactpy_flake8/exhaustive_deps.py
reactpy_flake8/flake8_plugin.py
reactpy_flake8/rules_of_hooks.py
reactpy_flake8/run.py
reactpy_flake8-0.7.0.dist-info/LICENSE
reactpy_flake8-0.7.0.dist-info/METADATA
reactpy_flake8-0.7.0.dist-info/WHEEL
reactpy_flake8-0.7.0.dist-info/entry_points.txt
reactpy_flake8-0.7.0.dist-info/top_level.txt
reactpy_flake8-0.7.0.dist-info/RECORD
